quant_data/__init__.py
quant_data/client.py
quant_data/readers/__init__.py
quant_data/readers/daily.py
quant_data/readers/dim.py
quant_data/readers/finance.py
quant_data/utils/__init__.py
mmdata_sdk-0.2.dist-info/METADATA
mmdata_sdk-0.2.dist-info/WHEEL
mmdata_sdk-0.2.dist-info/top_level.txt
mmdata_sdk-0.2.dist-info/RECORD
