Metadata-Version: 2.4
Name: mmdata-sdk
Version: 0.2
Summary: 量化研究数据 SDK，提供 StarRocks DWD/DIM 层数据便捷查询
Home-page: 
Author: MM Team
Author-email: MM Team <MMTeam@example.com>
License: MIT
Project-URL: Homepage, https://docs.starrocks.io/zh/docs/3.5/introduction/StarRocks_intro/
Project-URL: Repository, https://docs.starrocks.io/zh/docs/3.5/introduction/StarRocks_intro/
Classifier: Development Status :: 3 - Alpha
Classifier: Intended Audience :: Developers
Classifier: Intended Audience :: Financial and Insurance Industry
Classifier: License :: OSI Approved :: MIT License
Classifier: Operating System :: OS Independent
Classifier: Programming Language :: Python :: 3
Classifier: Programming Language :: Python :: 3.9
Classifier: Programming Language :: Python :: 3.10
Classifier: Programming Language :: Python :: 3.11
Classifier: Topic :: Office/Business :: Financial :: Investment
Requires-Python: >=3.9
Requires-Dist: pandas>=2.0.0
Requires-Dist: numpy>=1.24.0
Requires-Dist: pymysql>=1.1.0
Requires-Dist: dbutils>=3.0.0
Requires-Dist: loguru>=0.7.0
Requires-Dist: requests>=2.28.0
Provides-Extra: dev
Requires-Dist: pytest>=7.0.0; extra == "dev"
Requires-Dist: pytest-cov>=4.0.0; extra == "dev"
Dynamic: author
Dynamic: requires-python
